ClusterMimsy/__init__.py
ClusterMimsy/ccc_algorithm.py
ClusterMimsy/hello.py
ClusterMimsy/information_utils.py
ClusterMimsy/smile.py
ClusterMimsy/data_files/play_data.py
ClusterMimsy/nest/__init__.py
ClusterMimsy/nest/advice.py
ClusterMimsy/tests/__init__.py
ClusterMimsy/tests/test_advice.py
ClusterMimsy/tests/test_hello.py
ClusterMimsy/tests/test_smiles.py
ClusterMimsy-0.0.41.dist-info/METADATA
ClusterMimsy-0.0.41.dist-info/WHEEL
ClusterMimsy-0.0.41.dist-info/top_level.txt
ClusterMimsy-0.0.41.dist-info/RECORD
