Metadata-Version: 2.1
Name: ClusterMimsy
Version: 0.0.41
Summary: A package for the ClusterMI algorithm
Author: ClusterMimsyDev
Author-email: <ClusterMimsyDev@gmail.com>
Keywords: python,first package
Classifier: Development Status :: 3 - Alpha
Classifier: Intended Audience :: Education
Classifier: Programming Language :: Python :: 3
Classifier: Operating System :: Microsoft :: Windows
Requires-Dist: numpy
Requires-Dist: pandas
Requires-Dist: scipy
Requires-Dist: scikit-learn
